pycnite/__init__.py
pycnite/__version__.py
pycnite/bytecode.py
pycnite/linetable.py
pycnite/magic.py
pycnite/mapping.py
pycnite/marshal.py
pycnite/pyc.py
pycnite/types.py
pycnite-2024.7.9.dist-info/LICENSE
pycnite-2024.7.9.dist-info/METADATA
pycnite-2024.7.9.dist-info/WHEEL
pycnite-2024.7.9.dist-info/top_level.txt
pycnite-2024.7.9.dist-info/RECORD
